durable_rules_tools/__init__.py
durable_rules_tools/magic.py
durable_rules_tools/rules_utils.py
durable_rules_tools-0.0.1.dist-info/LICENSE
durable_rules_tools-0.0.1.dist-info/METADATA
durable_rules_tools-0.0.1.dist-info/WHEEL
durable_rules_tools-0.0.1.dist-info/top_level.txt
durable_rules_tools-0.0.1.dist-info/RECORD
