Metadata-Version: 2.1
Name: durable-rules-tools
Version: 0.0.1
Summary: IPyhon magics for durable rules.
Home-page: UNKNOWN
Author: Tony Hirst
Author-email: tony.hirst@open.ac.uk
License: MIT License
Platform: UNKNOWN
Requires-Dist: durable-rules
